passw0rts/__init__.py
passw0rts/cli/__init__.py
passw0rts/cli/clipboard_handler.py
passw0rts/cli/main.py
passw0rts/core/__init__.py
passw0rts/core/encryption.py
passw0rts/core/password_entry.py
passw0rts/core/storage.py
passw0rts/utils/__init__.py
passw0rts/utils/daemon_manager.py
passw0rts/utils/password_generator.py
passw0rts/utils/session_manager.py
passw0rts/utils/session_persistence.py
passw0rts/utils/totp_manager.py
passw0rts/utils/usb_key_manager.py
passw0rts/web/__init__.py
passw0rts/web/app.py
passw0rts/web/daemon.py
passw0rts/web/templates/base.html
passw0rts/web/templates/dashboard.html
passw0rts/web/templates/init.html
passw0rts/web/templates/login.html
passw0rts-0.2.dist-info/licenses/LICENSE
passw0rts-0.2.dist-info/METADATA
passw0rts-0.2.dist-info/WHEEL
passw0rts-0.2.dist-info/entry_points.txt
passw0rts-0.2.dist-info/top_level.txt
passw0rts-0.2.dist-info/RECORD
