Metadata-Version: 2.4
Name: passw0rts
Version: 0.2
Summary: A secure cross-platform password manager with CLI and web UI
Home-page: https://github.com/RiseofRice/passw0rts
Author: RiseofRice
License: MIT
Project-URL: Homepage, https://github.com/RiseofRice/passw0rts
Project-URL: Repository, https://github.com/RiseofRice/passw0rts
Project-URL: Issues, https://github.com/RiseofRice/passw0rts/issues
Project-URL: Documentation, https://github.com/RiseofRice/passw0rts#readme
Keywords: password-manager,security,encryption,cli,2fa,totp,usb-key,yubikey,password-generator
Classifier: Development Status :: 3 - Alpha
Classifier: Intended Audience :: End Users/Desktop
Classifier: License :: OSI Approved :: MIT License
Classifier: Programming Language :: Python :: 3
Classifier: Programming Language :: Python :: 3.8
Classifier: Programming Language :: Python :: 3.9
Classifier: Programming Language :: Python :: 3.10
Classifier: Programming Language :: Python :: 3.11
Classifier: Programming Language :: Python :: 3.12
Classifier: Operating System :: OS Independent
Classifier: Topic :: Security
Classifier: Topic :: Security :: Cryptography
Classifier: Topic :: Utilities
Requires-Python: >=3.8
License-File: LICENSE
Requires-Dist: cryptography>=41.0.7
Requires-Dist: pyotp>=2.9.0
Requires-Dist: qrcode>=8.0
Requires-Dist: pyusb>=1.2.1
Requires-Dist: click>=8.1.7
Requires-Dist: rich>=13.7.0
Requires-Dist: pyperclip>=1.8.2
Requires-Dist: flask>=3.0.0
Requires-Dist: flask-cors>=4.0.0
Requires-Dist: pydantic>=2.5.3
Provides-Extra: dev
Requires-Dist: pytest>=7.4.3; extra == "dev"
Requires-Dist: pytest-cov>=4.1.0; extra == "dev"
Requires-Dist: build>=1.0.0; extra == "dev"
Requires-Dist: twine>=4.0.0; extra == "dev"
Dynamic: home-page
Dynamic: license-file
Dynamic: requires-python
